JellyDog/__init__.py
JellyDog-0.1.3.dist-info/LICENSE
JellyDog-0.1.3.dist-info/METADATA
JellyDog-0.1.3.dist-info/WHEEL
JellyDog-0.1.3.dist-info/top_level.txt
JellyDog-0.1.3.dist-info/RECORD
