Metadata-Version: 2.1
Name: JellyDog
Version: 0.1.3
Summary: A JellyCat online store stock tracker
Home-page: https://github.com/Akuna23Matata/JellyDog
Author: Akuna23Matata
Author-email: zhiboh23@gmail.com
License: MIT
License-File: LICENSE
Requires-Dist: bs4
